fusionexport/__init__.py
fusionexport/constants.py
fusionexport/converters.py
fusionexport/export_config.py
fusionexport/export_error.py
fusionexport/export_manager.py
fusionexport/typings.py
fusionexport/utils.py
fusionexport-2.0.0.dist-info/LICENSE
fusionexport-2.0.0.dist-info/METADATA
fusionexport-2.0.0.dist-info/WHEEL
fusionexport-2.0.0.dist-info/top_level.txt
fusionexport-2.0.0.dist-info/RECORD
