Metadata-Version: 2.1
Name: fusionexport
Version: 2.0.0
Summary: The FusionExport SDK in Python
Home-page: https://github.com/fusioncharts/fusionexport-python-client
Author: FusionCharts
Author-email: fusionexport@fusioncharts.com
License: MIT
Keywords: fusionexport fusioncharts sdk charts export python dashboards language client cli console
Platform: UNKNOWN
License-File: LICENSE
Requires-Dist: requests
Requires-Dist: glob2
Requires-Dist: beautifulsoup4
Requires-Dist: html-minifier
Requires-Dist: jsmin
